sphinxcontrib_lunrsearch-0.4-py3.9-nspkg.pth
sphinxcontrib/lunrsearch/__init__.py
sphinxcontrib/lunrsearch/searchbox.html
sphinxcontrib/lunrsearch/css/searchbox.css
sphinxcontrib/lunrsearch/js/searchbox.js
sphinxcontrib_lunrsearch-0.4.dist-info/LICENSE
sphinxcontrib_lunrsearch-0.4.dist-info/METADATA
sphinxcontrib_lunrsearch-0.4.dist-info/WHEEL
sphinxcontrib_lunrsearch-0.4.dist-info/namespace_packages.txt
sphinxcontrib_lunrsearch-0.4.dist-info/top_level.txt
sphinxcontrib_lunrsearch-0.4.dist-info/RECORD
