Metadata-Version: 2.1
Name: sphinxcontrib-lunrsearch
Version: 0.4
Summary: Instant search for Sphinx
Home-page: https://github.com/rmcgibbo/sphinxcontrib-lunrsearch
Author: Robert T. McGibbon
Author-email: rmcgibbo@gmail.com
License: MIT
Download-URL: https://pypi.python.org/pypi/sphinxcontrib-lunrsearch
Platform: any
Classifier: Development Status :: 3 - Alpha
Classifier: Environment :: Console
Classifier: Environment :: Web Environment
Classifier: Intended Audience :: Developers
Classifier: License :: OSI Approved :: MIT License
Classifier: Operating System :: OS Independent
Classifier: Programming Language :: Python
Classifier: Programming Language :: Python :: 2
Classifier: Programming Language :: Python :: 2.7
Classifier: Programming Language :: Python :: 3
Classifier: Programming Language :: Python :: 3.5
Classifier: Programming Language :: Python :: 3.6
Classifier: Programming Language :: Python :: Implementation :: CPython
Classifier: Programming Language :: Python :: Implementation :: PyPy
Classifier: Topic :: Documentation
Classifier: Topic :: Utilities
Requires-Dist: Sphinx (>=1.0)
Requires-Dist: six (>=1.4.1)
